gnukek_cli/__init__.py
gnukek_cli/__main__.py
gnukek_cli/command_handlers/__init__.py
gnukek_cli/command_handlers/decrypt.py
gnukek_cli/command_handlers/delete_key.py
gnukek_cli/command_handlers/encrypt.py
gnukek_cli/command_handlers/export.py
gnukek_cli/command_handlers/generate.py
gnukek_cli/command_handlers/import_keys.py
gnukek_cli/command_handlers/list_keys.py
gnukek_cli/command_handlers/sign.py
gnukek_cli/command_handlers/verify.py
gnukek_cli/command_handlers/version.py
gnukek_cli/commands/__init__.py
gnukek_cli/commands/decrypt.py
gnukek_cli/commands/delete_key.py
gnukek_cli/commands/edit.py
gnukek_cli/commands/encrypt.py
gnukek_cli/commands/export.py
gnukek_cli/commands/generate.py
gnukek_cli/commands/import_keys.py
gnukek_cli/commands/list_keys.py
gnukek_cli/commands/sign.py
gnukek_cli/commands/verify.py
gnukek_cli/commands/version.py
gnukek_cli/config.py
gnukek_cli/constants.py
gnukek_cli/container.py
gnukek_cli/entrypoint.py
gnukek_cli/extras/__init__.py
gnukek_cli/extras/s3/__init__.py
gnukek_cli/extras/s3/buffers.py
gnukek_cli/extras/s3/command_handlers/__init__.py
gnukek_cli/extras/s3/command_handlers/download.py
gnukek_cli/extras/s3/command_handlers/upload.py
gnukek_cli/extras/s3/commands/__init__.py
gnukek_cli/extras/s3/commands/download.py
gnukek_cli/extras/s3/commands/upload.py
gnukek_cli/extras/s3/constants.py
gnukek_cli/extras/s3/helpers.py
gnukek_cli/keys/__init__.py
gnukek_cli/keys/provider.py
gnukek_cli/keys/storages.py
gnukek_cli/utils/__init__.py
gnukek_cli/utils/completions.py
gnukek_cli/utils/exceptions.py
gnukek_cli/utils/logger.py
gnukek_cli/utils/monitoring.py
gnukek_cli/utils/passwords.py
gnukek_cli-1.1.1.dist-info/LICENSE
gnukek_cli-1.1.1.dist-info/METADATA
gnukek_cli-1.1.1.dist-info/WHEEL
gnukek_cli-1.1.1.dist-info/entry_points.txt
gnukek_cli-1.1.1.dist-info/RECORD
